og_sdk/__init__.py
og_sdk/agent_sdk.py
og_sdk/kernel_sdk.py
og_sdk/utils.py
og_sdk-0.5.3.dist-info/METADATA
og_sdk-0.5.3.dist-info/WHEEL
og_sdk-0.5.3.dist-info/top_level.txt
og_sdk-0.5.3.dist-info/RECORD
