Metadata-Version: 2.1
Name: og-sdk
Version: 0.5.3
Summary: Open source code interpreter agent for LLM
Home-page: https://github.com/dbpunk-labs/octogen
Author: imotai
Author-email: codego.me@gmail.com
Requires-Dist: og-proto
Requires-Dist: aiofiles
